leadtools_common_runtime/__init__.py
leadtools_common_runtime/__pkginfo__.py
leadtools_common_runtime/bin/Common/OcrLEADRuntime/BusinessCard.Names.en.dic
leadtools_common_runtime/bin/Common/OcrLEADRuntime/BusinessCard.Titles.en.dic
leadtools_common_runtime/bin/Common/OcrLEADRuntime/LEAD.Binarize.bin
leadtools_common_runtime/bin/Common/OcrLEADRuntime/LEAD.Cmc7.bin
leadtools_common_runtime/bin/Common/OcrLEADRuntime/LEAD.Field.bin
leadtools_common_runtime/bin/Common/OcrLEADRuntime/LEAD.Micr.bin
leadtools_common_runtime/bin/Common/OcrLEADRuntime/LEAD.Mrz.bin
leadtools_common_runtime/bin/Common/OcrLEADRuntime/LEAD.de.bin
leadtools_common_runtime/bin/Common/OcrLEADRuntime/LEAD.de.dic
leadtools_common_runtime/bin/Common/OcrLEADRuntime/LEAD.en.bin
leadtools_common_runtime/bin/Common/OcrLEADRuntime/LEAD.en.bin2
leadtools_common_runtime/bin/Common/OcrLEADRuntime/LEAD.en.dic
leadtools_common_runtime/bin/Common/OcrLEADRuntime/LEAD.es.bin
leadtools_common_runtime/bin/Common/OcrLEADRuntime/LEAD.es.dic
leadtools_common_runtime/bin/Common/OcrLEADRuntime/LEAD.fr.bin
leadtools_common_runtime/bin/Common/OcrLEADRuntime/LEAD.fr.dic
leadtools_common_runtime/bin/Common/OcrLEADRuntime/LEAD.icr.en.p1.bin
leadtools_common_runtime/bin/Common/OcrLEADRuntime/LEAD.icr.en.p2.bin
leadtools_common_runtime/bin/Common/OcrLEADRuntime/LEAD.icr.en.p3.bin
leadtools_common_runtime/bin/Common/OcrLEADRuntime/LEAD.icr.en.p4.bin
leadtools_common_runtime/bin/Common/OcrLEADRuntime/LEAD.icr.en.p5.bin
leadtools_common_runtime/bin/Common/OcrLEADRuntime/LEAD.icr.en.p6.bin
leadtools_common_runtime/bin/Common/OcrLEADRuntime/LEAD.icr.en.p7.bin
leadtools_common_runtime/bin/Common/OcrLEADRuntime/LEAD.icr.en.p8.bin
leadtools_common_runtime/bin/Common/OcrLEADRuntime/LEAD.it.bin
leadtools_common_runtime/bin/Common/OcrLEADRuntime/LEAD.it.dic
leadtools_common_runtime/bin/Common/OcrLEADRuntime/LEAD.ja.bin
leadtools_common_runtime/bin/Common/OcrLEADRuntime/LEAD.ja.bin2
leadtools_common_runtime-23.0.0.5.dist-info/licenses/LICENSE
leadtools_common_runtime-23.0.0.5.dist-info/METADATA
leadtools_common_runtime-23.0.0.5.dist-info/WHEEL
leadtools_common_runtime-23.0.0.5.dist-info/top_level.txt
leadtools_common_runtime-23.0.0.5.dist-info/RECORD
