Metadata-Version: 2.4
Name: leadtools_common_runtime
Version: 23.0.0.5
Summary: This package is not intended for direct use. This package contains runtime data files for use by LEADTOOLS.
Author-email: "LEAD Technologies, Inc." <support@leadtools.com>
License: 
Project-URL: Homepage, https://www.leadtools.com
Project-URL: Documentation, https://www.leadtools.com/support/webhelp
Project-URL: Chat, https://www.leadtools.com/support/chat
Keywords: leadtools,lead-tools
Classifier: Programming Language :: Python :: 3
Classifier: License :: Other/Proprietary License
Classifier: Operating System :: OS Independent
Classifier: Development Status :: 5 - Production/Stable
Classifier: Intended Audience :: Developers
Classifier: Programming Language :: C#
Classifier: Programming Language :: Python
Classifier: Topic :: Software Development :: Build Tools
Requires-Python: >=3.7
License-File: LICENSE
Dynamic: license-file
